paperflow/__init__.py
paperflow/cli.py
paperflow/pipeline.py
paperflow/processors/__init__.py
paperflow/processors/chunker.py
paperflow/processors/embeddings.py
paperflow/processors/marker_processor.py
paperflow/providers/__init__.py
paperflow/providers/arxiv_provider.py
paperflow/providers/base.py
paperflow/providers/openalex_provider.py
paperflow/providers/pubmed_provider.py
paperflow/providers/semantic_scholar_provider.py
paperflow/schemas/__init__.py
paperflow/schemas/paper.py
paperflow-0.1.14.dist-info/METADATA
paperflow-0.1.14.dist-info/WHEEL
paperflow-0.1.14.dist-info/entry_points.txt
paperflow-0.1.14.dist-info/top_level.txt
paperflow-0.1.14.dist-info/RECORD
