Metadata-Version: 2.4
Name: paperflow
Version: 0.1.14
Summary: Unified paper ingestion, extraction, and RAG pipeline
Author-email: Ali Nemati <alinemati@osllm.ai>
License-Expression: MIT
Project-URL: Homepage, https://github.com/osllmai/paperflow
Project-URL: Documentation, https://github.com/osllmai/paperflow#readme
Project-URL: Repository, https://github.com/osllmai/paperflow
Project-URL: Issues, https://github.com/osllmai/paperflow/issues
Keywords: academic,papers,arxiv,pubmed,semantic-scholar,pdf,extraction,rag,langchain,research
Classifier: Development Status :: 3 - Alpha
Classifier: Intended Audience :: Science/Research
Classifier: Programming Language :: Python :: 3
Classifier: Programming Language :: Python :: 3.9
Classifier: Programming Language :: Python :: 3.10
Classifier: Programming Language :: Python :: 3.11
Classifier: Programming Language :: Python :: 3.12
Classifier: Topic :: Scientific/Engineering
Classifier: Topic :: Text Processing
Requires-Python: >=3.9
Requires-Dist: pydantic>=2.0
Requires-Dist: httpx>=0.25.0
Requires-Dist: arxiv>=2.0.0
Requires-Dist: biopython>=1.80
Requires-Dist: requests>=2.28.0
Requires-Dist: tabulate>=0.9.0
Requires-Dist: numpy<2.0
Requires-Dist: opentelemetry-api==1.37.0
Requires-Dist: opentelemetry-sdk==1.37.0
Requires-Dist: opentelemetry-proto==1.37.0
Requires-Dist: opentelemetry-exporter-otlp-proto-common==1.37.0
Requires-Dist: opentelemetry-semantic-conventions==0.58b0
Provides-Extra: all
Requires-Dist: paperscraper>=0.3.0; extra == "all"
Requires-Dist: pyalex>=0.13; extra == "all"
Requires-Dist: semanticscholar>=0.8.0; extra == "all"
Requires-Dist: marker-pdf>=0.2.0; extra == "all"
Requires-Dist: langchain>=0.1.0; extra == "all"
Requires-Dist: chromadb>=0.4.0; extra == "all"
Requires-Dist: sentence-transformers>=2.2.0; extra == "all"
Requires-Dist: opentelemetry-api==1.37.0; extra == "all"
Requires-Dist: opentelemetry-sdk==1.37.0; extra == "all"
Requires-Dist: opentelemetry-proto==1.37.0; extra == "all"
Requires-Dist: opentelemetry-exporter-otlp-proto-common==1.37.0; extra == "all"
Requires-Dist: opentelemetry-semantic-conventions==0.58b0; extra == "all"
Provides-Extra: extraction
Requires-Dist: marker-pdf>=0.2.0; extra == "extraction"
Provides-Extra: extraction-light
Requires-Dist: markitdown>=0.1.0; extra == "extraction-light"
Requires-Dist: opentelemetry-api==1.37.0; extra == "extraction-light"
Requires-Dist: opentelemetry-sdk==1.37.0; extra == "extraction-light"
Requires-Dist: opentelemetry-proto==1.37.0; extra == "extraction-light"
Requires-Dist: opentelemetry-exporter-otlp-proto-common==1.37.0; extra == "extraction-light"
Requires-Dist: opentelemetry-semantic-conventions==0.58b0; extra == "extraction-light"
Provides-Extra: extraction-docling
Requires-Dist: docling>=2.0.0; extra == "extraction-docling"
Requires-Dist: opentelemetry-api==1.37.0; extra == "extraction-docling"
Requires-Dist: opentelemetry-sdk==1.37.0; extra == "extraction-docling"
Requires-Dist: opentelemetry-proto==1.37.0; extra == "extraction-docling"
Requires-Dist: opentelemetry-exporter-otlp-proto-common==1.37.0; extra == "extraction-docling"
Requires-Dist: opentelemetry-semantic-conventions==0.58b0; extra == "extraction-docling"
Provides-Extra: extraction-all
Requires-Dist: marker-pdf>=0.2.0; extra == "extraction-all"
Requires-Dist: markitdown>=0.1.0; extra == "extraction-all"
Requires-Dist: docling>=2.0.0; extra == "extraction-all"
Requires-Dist: opentelemetry-api==1.37.0; extra == "extraction-all"
Requires-Dist: opentelemetry-sdk==1.37.0; extra == "extraction-all"
Requires-Dist: opentelemetry-proto==1.37.0; extra == "extraction-all"
Requires-Dist: opentelemetry-exporter-otlp-proto-common==1.37.0; extra == "extraction-all"
Requires-Dist: opentelemetry-semantic-conventions==0.58b0; extra == "extraction-all"
Provides-Extra: rag
Requires-Dist: langchain>=0.1.0; extra == "rag"
Requires-Dist: chromadb>=0.4.0; extra == "rag"
Requires-Dist: sentence-transformers>=2.2.0; extra == "rag"
Provides-Extra: providers
Requires-Dist: paperscraper>=0.3.0; extra == "providers"
Requires-Dist: pyalex>=0.13; extra == "providers"
Requires-Dist: semanticscholar>=0.8.0; extra == "providers"
Provides-Extra: dev
Requires-Dist: pytest>=7.0; extra == "dev"
Requires-Dist: pytest-asyncio>=0.21.0; extra == "dev"
Requires-Dist: black>=23.0; extra == "dev"
Requires-Dist: ruff>=0.1.0; extra == "dev"
Requires-Dist: mypy>=1.0; extra == "dev"
